nzshm_common/__init__.py
nzshm_common/constants.py
nzshm_common/geometry/geometry.py
nzshm_common/grids/__init__.py
nzshm_common/grids/io.py
nzshm_common/grids/nz_0_1_nb_1_v0.py
nzshm_common/grids/nz_0_1_nb_1_v1.py
nzshm_common/grids/nz_0_2_nb_1_1.py
nzshm_common/grids/region_grid.py
nzshm_common/grids/wlg_0_01_nb_1_1.py
nzshm_common/grids/wlg_0_05_nb_1_1.py
nzshm_common/location/__init__.py
nzshm_common/location/coded_location.py
nzshm_common/location/location.py
nzshm_common/location/resources/__init__.py
nzshm_common/location/resources/locations.json
nzshm_common/location/resources/maori_names.csv
nzshm_common/location/resources/nz_ids.json
nzshm_common/location/types.py
nzshm_common/util/__init__.py
nzshm_common/util/compression.py
nzshm_common-0.9.1.dist-info/METADATA
nzshm_common-0.9.1.dist-info/WHEEL
nzshm_common-0.9.1.dist-info/licenses/LICENSE
nzshm_common-0.9.1.dist-info/RECORD
