Metadata-Version: 2.4
Name: nzshm-common
Version: 0.9.1
Summary: A small pure python library for shared NZ NSHM data like locations.
License-Expression: AGPL-3.0-or-later
License-File: LICENSE
Author: Chris B Chamberlain
Author-email: chrisbc@artisan.co.nz
Requires-Python: >=3.10,<4.0
Classifier: Development Status :: 2 - Pre-Alpha
Classifier: Intended Audience :: Developers
Classifier: Natural Language :: English
Classifier: Programming Language :: Python :: 3
Provides-Extra: geometry
Requires-Dist: shapely ; extra == "geometry"
